paymentech/__init__.py
paymentech/exceptions.py
paymentech/service.py
paymentech/version.py
paymentech/resources/__init__.py
paymentech/resources/authorization.py
paymentech/resources/base.py
paymentech/resources/inquiry.py
paymentech/resources/order.py
paymentech/resources/profile.py
paymentech/resources/reversal.py
paymentech-0.4.3.dist-info/licenses/LICENSE
tests/__init__.py
tests/test_configuration.py
tests/test_sanity.py
paymentech-0.4.3.dist-info/METADATA
paymentech-0.4.3.dist-info/WHEEL
paymentech-0.4.3.dist-info/top_level.txt
paymentech-0.4.3.dist-info/RECORD
